packer.py
robbiblubber.spellbook.backpack-0.0.1.dist-info/LICENSE
robbiblubber.spellbook.backpack-0.0.1.dist-info/METADATA
robbiblubber.spellbook.backpack-0.0.1.dist-info/WHEEL
robbiblubber.spellbook.backpack-0.0.1.dist-info/top_level.txt
robbiblubber.spellbook.backpack-0.0.1.dist-info/RECORD
